ask8ball/__init__.py
ask8ball/answers.txt
ask8ball/cli.py
ask8ball-1.0.0.dist-info/licenses/LICENSE
ask8ball-1.0.0.dist-info/METADATA
ask8ball-1.0.0.dist-info/WHEEL
ask8ball-1.0.0.dist-info/entry_points.txt
ask8ball-1.0.0.dist-info/top_level.txt
ask8ball-1.0.0.dist-info/RECORD
