Metadata-Version: 2.4
Name: ask8ball
Version: 1.0.0
Summary: A classic Magic 8-Ball for your terminal.
Author-email: Manasvi Bathula <manasvi.bathula@gmail.com>
License: Copyright (c) 2025 Manasvi Bathula
Classifier: Programming Language :: Python :: 3
Classifier: License :: OSI Approved :: MIT License
Classifier: Operating System :: OS Independent
Classifier: Topic :: Games/Entertainment
Requires-Python: >=3.8
License-File: LICENSE
Dynamic: license-file
